cookiecutter_poetry_example/__init__.py
cookiecutter_poetry_example/foo.py
cookiecutter_poetry_example-0.4.6.dist-info/LICENSE
cookiecutter_poetry_example-0.4.6.dist-info/WHEEL
cookiecutter_poetry_example-0.4.6.dist-info/METADATA
cookiecutter_poetry_example-0.4.6.dist-info/RECORD
