Metadata-Version: 2.1
Name: cookiecutter-poetry-example
Version: 0.4.6
Summary: This is a template repository for Python projects that use Poetry for their dependency management.
Home-page: https://github.com/fpgmaas/cookiecutter-poetry-example
Author: Florian Maas
Author-email: ffpgmaas@gmail.com
Requires-Python: >=3.8,<=3.11
Classifier: Programming Language :: Python :: 3
Classifier: Programming Language :: Python :: 3.8
Classifier: Programming Language :: Python :: 3.9
Classifier: Programming Language :: Python :: 3.10
Classifier: Programming Language :: Python :: 3.11
Project-URL: Documentation, https://fpgmaas.github.io/cookiecutter-poetry-example/
Project-URL: Repository, https://github.com/fpgmaas/cookiecutter-poetry-example
